README.md
setup.py
d4/__init__.py
d4/d4.py
d4.egg-info/PKG-INFO
d4.egg-info/SOURCES.txt
d4.egg-info/dependency_links.txt
d4.egg-info/entry_points.txt
d4.egg-info/requires.txt
d4.egg-info/top_level.txt
d4/__pycache__/__init__.cpython-34.pyc
d4/__pycache__/d3.cpython-34.pyc
d4/__pycache__/d4.cpython-34.pyc
d4/data/Dockerfile
d4/data/build.yaml
d4/data/common.yaml
d4/data/tests/config.yaml
tests/__init__.py
tests/test_build.py
tests/test_init.py
tests/test_main_build.py
tests/test_main_develop.py
tests/test_main_init.py
tests/test_main_test.py
tests/test_main_version.py
tests/test_test.py
tests/test_version.py