Metadata-Version: 2.1
Name: d4
Version: 0.1.8
Summary: Dock to Develop Dynamic Dockerfile
Home-page: https://github.com/pypa/d4
Author: Tatsunori Saito
Author-email: bbrfkr@gmail.com
License: UNKNOWN
Platform: UNKNOWN
Classifier: Programming Language :: Python :: 3
Classifier: License :: OSI Approved :: MIT License
Classifier: Operating System :: POSIX :: Linux
